minushalf-1.7.dist-info/LICENSE
minushalf-1.7.dist-info/METADATA
minushalf-1.7.dist-info/top_level.txt
minushalf-1.7.dist-info/RECORD
minushalf-1.7.dist-info/entry_points.txt
minushalf-1.7.dist-info/WHEEL
minushalf/atomic_program.cpython-36m-x86_64-linux-gnu.so
minushalf/minushalf.py
minushalf/__init__.py
minushalf/utils/negative_band_gap.py
minushalf/utils/get_correction_params.py
minushalf/utils/fractionary_correction_indexes.py
minushalf/utils/parse_valence_orbital_line.py
minushalf/utils/atomic_potential.py
minushalf/utils/cli_messages.py
minushalf/utils/check_file_exists.py
minushalf/utils/correct_potential_fourier_transform.py
minushalf/utils/projection_to_df.py
minushalf/utils/simple_correction_indexes.py
minushalf/utils/band_structure.py
minushalf/utils/parse_cut.py
minushalf/utils/drop_comments.py
minushalf/utils/cut_initial_guess.py
minushalf/utils/__init__.py
minushalf/utils/trimming_function.py
minushalf/commands/vbm_character.py
minushalf/commands/create_input.py
minushalf/commands/run_atomic_program.py
minushalf/commands/band_gap.py
minushalf/commands/cbm_character.py
minushalf/commands/execute.py
minushalf/commands/band_character.py
minushalf/commands/fractional_occupation.py
minushalf/commands/__init__.py
minushalf/commands/correct_potfile.py
minushalf/interfaces/software_abstract_factory.py
minushalf/interfaces/minushalf_yaml_tags.py
minushalf/interfaces/minushalf_yaml.py
minushalf/interfaces/potential_file.py
minushalf/interfaces/runner.py
minushalf/interfaces/band_projection_file.py
minushalf/interfaces/correction.py
minushalf/interfaces/handler.py
minushalf/interfaces/__init__.py
minushalf/data/correction_code.py
minushalf/data/orbital.py
minushalf/data/minushalf_yaml_default_configuration.py
minushalf/data/periodic_table.py
minushalf/data/cut_initial_guess_methods.py
minushalf/data/constants.py
minushalf/data/exchange_correlation.py
minushalf/data/electronic_distribution.py
minushalf/data/__init__.py
minushalf/data/softwares.py
minushalf/data/calculation_code.py
minushalf/io/make_minushalf_results.py
minushalf/io/minushalf_yaml.py
minushalf/io/atomic_program.py
minushalf/io/correction.py
