Metadata-Version: 2.1
Name: minushalf
Version: 1.7
Summary: CLI to provides Pre processing tools for DFT -1/2 calculations
Home-page: UNKNOWN
Author: Henrique Fernandes
Author-email: dftminushalf@gmail.com
License: GPL
Platform: UNKNOWN
License-File: LICENSE
Requires-Dist: pandas (>=1.1.5)
Requires-Dist: fortranformat (>=0.2.5)
Requires-Dist: Click (>=7.1.2)
Requires-Dist: pyfiglet (>=0.8)
Requires-Dist: loguru (>=0.5.3)
Requires-Dist: tabulate (>=0.8.7)
Requires-Dist: numpy (<=1.21.0)
Requires-Dist: pyyaml
Requires-Dist: scipy (>=1.5.4)
Requires-Dist: aenum (>=3.0.0)
